pBaseParams/__init__.py
pBaseParams/pBaseParams.py
pbaseparams-1.0.1.dist-info/METADATA
pbaseparams-1.0.1.dist-info/WHEEL
pbaseparams-1.0.1.dist-info/top_level.txt
pbaseparams-1.0.1.dist-info/RECORD
