Metadata-Version: 2.4
Name: pBaseParams
Version: 1.0.1
Summary: A simple config watcher 
Author: PAT
Requires-Python: >=3.6
Requires-Dist: watchdog
Requires-Dist: pyyaml
Requires-Dist: opencv-python
Requires-Dist: numpy
Dynamic: author
Dynamic: description
Dynamic: description-content-type
Dynamic: requires-dist
Dynamic: requires-python
Dynamic: summary
